foliant/backends/mdtopdf.py
foliant/preprocessors/mdtopdf.py
foliantcontrib.mdtopdf-1.0.0.dist-info/LICENSE
foliantcontrib.mdtopdf-1.0.0.dist-info/METADATA
foliantcontrib.mdtopdf-1.0.0.dist-info/WHEEL
foliantcontrib.mdtopdf-1.0.0.dist-info/top_level.txt
foliantcontrib.mdtopdf-1.0.0.dist-info/RECORD
