Metadata-Version: 2.1
Name: foliantcontrib.mdtopdf
Version: 1.0.0
Summary: MdToPdf backend for Foliant documentation generator.
Home-page: https://github.com/foliant-docs/foliantcontrib.mdtopdf
Author: Daniel Minukhin
Author-email: ddddsa@gmail.com
License: MIT
Platform: any
Classifier: Development Status :: 5 - Production/Stable
Classifier: Environment :: Console
Classifier: Intended Audience :: Developers
Classifier: License :: OSI Approved :: MIT License
Classifier: Operating System :: OS Independent
Classifier: Programming Language :: Python
Classifier: Topic :: Documentation
Classifier: Topic :: Utilities
Classifier: Programming Language :: Python :: 3.6
Requires-Dist: foliant (>=1.0.8)
Requires-Dist: foliantcontrib.flatten (>=1.0.2)
